<?xml version="1.0" encoding="utf-8"?>
<IncrementalBankBuild Version="6" Flags="878078161">
	<Platform GUID="{6198C3A2-D8BC-4CB0-92D6-D1B8CBC9FB4E}">
		<Banks>
			<Language ID="393239870">
				<File Name="Init" Hash="160211075" Timestamp="1558618060"/>
				<File Name="MainSoundBank" Hash="2675931682" Timestamp="1558618060"/>
			</Language>
		</Banks>
		<XMLInfo>
			<Language ID="-1">
				<File Name="" Hash="1111515026" Timestamp="1558618060"/>
			</Language>
		</XMLInfo>
	</Platform>
</IncrementalBankBuild>
